aio_request/__init__.py
aio_request/aiohttp.py
aio_request/base.py
aio_request/circuit_breaker.py
aio_request/client.py
aio_request/context.py
aio_request/deadline.py
aio_request/deadline_provider.py
aio_request/delays_provider.py
aio_request/deprecated.py
aio_request/endpoint_provider.py
aio_request/httpx.py
aio_request/percentile_based_request_attempt_delays_provider.py
aio_request/pipeline.py
aio_request/priority.py
aio_request/py.typed
aio_request/request.py
aio_request/request_attempt_delays_provider.py
aio_request/request_response_observer.py
aio_request/request_strategy.py
aio_request/response_classifier.py
aio_request/setup.py
aio_request/transport.py
aio_request/utils.py
aio_request-0.2.6.dist-info/METADATA
aio_request-0.2.6.dist-info/WHEEL
aio_request-0.2.6.dist-info/licenses/LICENSE
aio_request-0.2.6.dist-info/RECORD
