Metadata-Version: 2.4
Name: aio-request
Version: 0.2.6
Summary: Various strategies for sending requests
Project-URL: Homepage, https://github.com/anna-money/aio-request
Author-email: Iurii Pliner <yury@anna.money>
License: MIT
License-File: LICENSE
Classifier: Development Status :: 5 - Production/Stable
Classifier: Environment :: Web Environment
Classifier: Framework :: AsyncIO
Classifier: Intended Audience :: Developers
Classifier: License :: OSI Approved :: MIT License
Classifier: Operating System :: OS Independent
Classifier: Programming Language :: Python :: 3
Classifier: Programming Language :: Python :: 3 :: Only
Classifier: Programming Language :: Python :: 3.11
Classifier: Programming Language :: Python :: 3.12
Classifier: Programming Language :: Python :: 3.13
Classifier: Programming Language :: Python :: 3.14
Classifier: Typing :: Typed
Requires-Python: >=3.11
Requires-Dist: multidict<7.0,>=4.5
Requires-Dist: yarl<2.0,>=1.12.0
Provides-Extra: dev
Requires-Dist: aiohttp==3.13.2; extra == 'dev'
Requires-Dist: httpx==0.28.1; extra == 'dev'
Requires-Dist: opentelemetry-api>=1.27; extra == 'dev'
Requires-Dist: opentelemetry-exporter-prometheus; extra == 'dev'
Requires-Dist: opentelemetry-instrumentation-aiohttp-client; extra == 'dev'
Requires-Dist: opentelemetry-semantic-conventions; extra == 'dev'
Requires-Dist: prometheus-client==0.23.1; extra == 'dev'
Requires-Dist: pyright==1.1.407; extra == 'dev'
Requires-Dist: pytest-aiohttp==1.1.0; extra == 'dev'
Requires-Dist: pytest-httpbin==2.1.0; extra == 'dev'
Requires-Dist: pytest==9.0.1; extra == 'dev'
Requires-Dist: ruff==0.14.7; extra == 'dev'
Requires-Dist: tdigest==0.5.2.2; extra == 'dev'
